tan.py
pyperclip/__init__.py
tan_up-0.0.3.dist-info/DESCRIPTION.rst
tan_up-0.0.3.dist-info/METADATA
tan_up-0.0.3.dist-info/RECORD
tan_up-0.0.3.dist-info/WHEEL
tan_up-0.0.3.dist-info/entry_points.txt
tan_up-0.0.3.dist-info/metadata.json
tan_up-0.0.3.dist-info/top_level.txt
